{
  "project_info": {
    "project_number": "533195333642",
    "project_id": "myapp-e0ce3",
    "storage_bucket": "myapp-e0ce3.firebasestorage.app"
  },
  "client": [
    {
      "client_info": {
        "mobilesdk_app_id": "1:533195333642:android:40eb173edf8b539f6e3ff3",
        "android_client_info": {
          "package_name": "com.mycompany.myapp"
        }
      },
      "oauth_client": [],
      "api_key": [
        {
          "current_key": "AIzaSyD1tddWsmuV6BU3emy47MHB1ejLrNyIwHc"
        }
      ],
      "services": {
        "appinvite_service": {
          "other_platform_oauth_client": []
        }
      }
    },
    {
      "client_info": {
        "mobilesdk_app_id": "1:533195333642:android:5eb954f7b5be59306e3ff3",
        "android_client_info": {
          "package_name": "com.mycompany.studyapp"
        }
      },
      "oauth_client": [],
      "api_key": [
        {
          "current_key": "AIzaSyD1tddWsmuV6BU3emy47MHB1ejLrNyIwHc"
        }
      ],
      "services": {
        "appinvite_service": {
          "other_platform_oauth_client": []
        }
      }
    }
  ],
  "configuration_version": "1"
}